{
  "$schema": "../gen/schemas/desktop-schema.json",
  "identifier": "default",
  "description": "Default capability for the main window with file system, shell and OS access",
  "windows": ["main", "logs", "mini-hud"],
  "permissions": [
    "core:default",
    "core:window:allow-start-dragging",
    "opener:default",
    "autostart:allow-enable",
    "autostart:allow-disable",
    "autostart:allow-is-enabled",
    "fs:default",
    "fs:allow-home-read-recursive",
    "fs:allow-home-write-recursive",
    "shell:allow-open",
    "shell:allow-execute",
    "os:default",
    "dialog:default"
  ]
}
